README.rst
setup.py
django_runprocess.egg-info/PKG-INFO
django_runprocess.egg-info/SOURCES.txt
django_runprocess.egg-info/dependency_links.txt
django_runprocess.egg-info/top_level.txt
runprocess/__init__.py
runprocess/management/__init__.py
runprocess/management/commands/__init__.py
runprocess/management/commands/runserver.py