Metadata-Version: 1.1
Name: django-runprocess
Version: 0.1.0
Summary: Runs processes along with runserver
Home-page: https://github.com/sephii/django-runprocess
Author: Sylvain Fankhauser
Author-email: sylvain@fankhauser.name
License: MIT
Platform: UNKNOWN
Classifier: Development Status :: 5 - Production/Stable
Classifier: Framework :: Django
Classifier: Intended Audience :: Developers
Classifier: License :: OSI Approved :: MIT License
Classifier: Topic :: Internet :: WWW/HTTP
